README.md
setup.py
SuperalloyDigger.egg-info/PKG-INFO
SuperalloyDigger.egg-info/SOURCES.txt
SuperalloyDigger.egg-info/dependency_links.txt
SuperalloyDigger.egg-info/top_level.txt
superalloydigger/__init__.py
superalloydigger/dictionary.py
superalloydigger/elsevier_articles_archive/__init__.py
superalloydigger/elsevier_articles_archive/article_dois.py
superalloydigger/get_doi/__init__.py
superalloydigger/get_doi/data_archive.py
superalloydigger/get_doi/doi_catch.py
superalloydigger/get_doi/httprequest.py
superalloydigger/get_full_text_from_html/__init__.py
superalloydigger/get_full_text_from_html/html_parser.py
superalloydigger/get_full_text_from_html/log_wp.py
superalloydigger/get_table_info/__init__.py
superalloydigger/get_table_info/elsevier_xml/__init__.py
superalloydigger/get_table_info/elsevier_xml/class_modified.py
superalloydigger/get_table_info/elsevier_xml/dictionary.py
superalloydigger/get_table_info/elsevier_xml/log_wp.py
superalloydigger/get_table_info/elsevier_xml/table.py
superalloydigger/get_table_info/other_journals_html/__init__.py
superalloydigger/get_table_info/other_journals_html/log_wp.py
superalloydigger/get_table_info/other_journals_html/table_info_get.py
superalloydigger/regular_table_extractor/Phrase_parse.py
superalloydigger/regular_table_extractor/Relation_extraciton_dp.py
superalloydigger/regular_table_extractor/Relation_extraciton_orig.py
superalloydigger/regular_table_extractor/T_pre_processor.py
superalloydigger/regular_table_extractor/__init__.py
superalloydigger/regular_table_extractor/dictionary.py
superalloydigger/regular_table_extractor/file_io.py
superalloydigger/regular_table_extractor/get_all_attributes.py
superalloydigger/regular_table_extractor/get_full_text.py
superalloydigger/regular_table_extractor/log_wp.py
superalloydigger/regular_table_extractor/output_modified_triple.py
superalloydigger/regular_table_extractor/pre_processor.py
superalloydigger/regular_table_extractor/sentence_positioner.py
superalloydigger/regular_table_extractor/table.py
superalloydigger/regular_table_extractor/table_extractor_modified.py
superalloydigger/regular_table_extractor/text_with_table.py
