Metadata-Version: 2.1
Name: SuperalloyDigger
Version: 0.1.5
Summary: Automatic extraction of chemical compositions and properties from the scientific literature of superalloy, covering specific chemical composition, density, solvus temperature, solidus temperature, and liquidus temperature.
Home-page: https://github.com/Weiren1996/superalloydigger
Author: Weiren_Wang
Author-email: 357329191@qq.com
License: MIT
Keywords: text-mining,superalloy,informatics,nlp,txt,science,scientific
Platform: UNKNOWN
Classifier: Environment :: Web Environment
Classifier: Intended Audience :: Science/Research
Classifier: Operating System :: Microsoft :: Windows
Classifier: Programming Language :: Python :: 3
Classifier: Topic :: Internet
Classifier: Topic :: Scientific/Engineering
Classifier: Topic :: Text Processing
Requires-Python: >=3.6
